[{"storeId": 6098, "lat": 11.56477, "lng": 107.83808, "storeLocation": "BHX 616 Nguy\u1ec5n V\u0103n C\u1eeb (S\u1ed1 618 Nguy\u1ec5n V\u0103n C\u1eeb, Ph\u01b0\u1eddng L\u1ed9c Ph\u00e1t, TP. B\u1ea3o L\u1ed9c, T\u1ec9nh L\u00e2m \u0110\u1ed3ng (\u0111\u1ed1i di\u1ec7n nh\u00e0 th\u1edd Th\u00e1nh M\u1eabu))", "provinceId": 129, "districtId": 1108, "wardId": 5467, "isStoreVirtual": false, "openHour": "5 gi\u1edd 30 ph\u00fat - 21 gi\u1edd 30 ph\u00fat (k\u1ec3 c\u1ea3 CN v\u00e0 ng\u00e0y l\u1ec5)"}, {"storeId": 6109, "lat": 11.547388, "lng": 107.81011, "storeLocation": "BHX 20 Nguy\u1ec5n C\u00f4ng Tr\u1ee9 (S\u1ed1 20 - 22 Nguy\u1ec5n C\u00f4ng Tr\u1ee9, Ph\u01b0\u1eddng 1, TP. B\u1ea3o L\u1ed9c, T\u1ec9nh L\u00e2m \u0110\u1ed3ng (ngay ch\u1ee3 B\u1ea3o L\u1ed9c c\u0169))", "provinceId": 129, "districtId": 1108, "wardId": 5464, "isStoreVirtual": false, "openHour": "5 gi\u1edd 30 ph\u00fat - 21 gi\u1edd 30 ph\u00fat (k\u1ec3 c\u1ea3 CN v\u00e0 ng\u00e0y l\u1ec5)"}, {"storeId": 6291, "lat": 11.540474, "lng": 107.823166, "storeLocation": "BHX 53 H\u00e0 Giang (S\u1ed1 53 H\u00e0 Giang, Ph\u01b0\u1eddng L\u1ed9c S\u01a1n, TP. B\u1ea3o L\u1ed9c, T\u1ec9nh L\u00e2m \u0110\u1ed3ng (ngay ch\u1ee3 T\u1ea1m H\u00e0 Giang))", "provinceId": 129, "districtId": 1108, "wardId": 5468, "isStoreVirtual": false, "openHour": "5 gi\u1edd 30 ph\u00fat - 21 gi\u1edd 30 ph\u00fat (k\u1ec3 c\u1ea3 CN v\u00e0 ng\u00e0y l\u1ec5)"}, {"storeId": 6110, "lat": 11.558438, "lng": 107.80568, "storeLocation": "BHX 2 Nguy\u1ec5n Th\u00e1i H\u1ecdc (S\u1ed1 2 Nguy\u1ec5n Th\u00e1i H\u1ecdc, Ph\u01b0\u1eddng 2, TP. B\u1ea3o L\u1ed9c, T\u1ec9nh L\u00e2m \u0110\u1ed3ng (ngay Tu\u1ea5n Nh\u01b0 Plaza - B'lao Plaza c\u0169))", "provinceId": 129, "districtId": 1108, "wardId": 5465, "isStoreVirtual": false, "openHour": "5 gi\u1edd 30 ph\u00fat - 21 gi\u1edd 30 ph\u00fat (k\u1ec3 c\u1ea3 CN v\u00e0 ng\u00e0y l\u1ec5)"}, {"storeId": 6891, "lat": 11.844173, "lng": 108.34266, "storeLocation": "BHX Ch\u1ee3 Th\u0103ng Long (Ch\u1ee3 Th\u0103ng Long, Th\u1ecb Tr\u1ea5n Nam Ban, Huy\u1ec7n L\u00e2m H\u00e0, T\u1ec9nh L\u00e2m \u0110\u1ed3ng (\u0111\u1ed1i di\u1ec7n ch\u1ee3 Th\u0103ng Long))", "provinceId": 129, "districtId": 1118, "wardId": 5433, "isStoreVirtual": false, "openHour": "5 gi\u1edd 30 ph\u00fat - 21 gi\u1edd (k\u1ec3 c\u1ea3 CN v\u00e0 ng\u00e0y l\u1ec5)"}, {"storeId": 6928, "lat": 11.761, "lng": 108.490585, "storeLocation": "BHX 220 \u0110\u01b0\u1eddng 2/4 (S\u1ed1 220 \u0110\u01b0\u1eddng 2/4, KP. Ngh\u0129a Th\u1ecb, TT. Th\u1ea1nh M\u1ef9, Huy\u1ec7n \u0110\u01a1n D\u01b0\u01a1ng, T\u1ec9nh L\u00e2m \u0110\u1ed3ng (ngay ng\u00e3 3 \u0111\u01b0\u1eddng 2/4 - \u00c2u C\u01a1))", "provinceId": 129, "districtId": 1115, "wardId": 5402, "isStoreVirtual": false, "openHour": "5 gi\u1edd 30 ph\u00fat - 21 gi\u1edd 30 ph\u00fat (k\u1ec3 c\u1ea3 CN v\u00e0 ng\u00e0y l\u1ec5)"}, {"storeId": 7104, "lat": 11.450193, "lng": 107.83436, "storeLocation": "BHX Qu\u1ed1c L\u1ed9 55 L\u1ed9c Th\u00e0nh (Th\u00f4n 8A, X\u00e3 L\u1ed9c Th\u00e0nh, Huy\u1ec7n B\u1ea3o L\u00e2m, T\u1ec9nh L\u00e2m \u0110\u1ed3ng (ngay ch\u1ee3 L\u1ed9c Th\u00e0nh))", "provinceId": 129, "districtId": 1107, "wardId": 11170, "isStoreVirtual": false, "openHour": "5 gi\u1edd 30 ph\u00fat - 21 gi\u1edd 30 ph\u00fat (k\u1ec3 c\u1ea3 CN v\u00e0 ng\u00e0y l\u1ec5)"}, {"storeId": 7172, "lat": 11.613593, "lng": 108.110504, "storeLocation": "BHX \u0110inh L\u1ea1c (S\u1ed1 14 Qu\u1ed1c L\u1ed9 20, Th\u00f4n \u0110\u1ed3ng L\u1ea1c 1, X\u00e3 \u0110inh L\u1ea1c, Huy\u1ec7n Di Linh, T\u1ec9nh L\u00e2m \u0110\u1ed3ng (c\u00e1ch ch\u1ee3 \u0110inh L\u1ea1c 50m))", "provinceId": 129, "districtId": 1114, "wardId": 5384, "isStoreVirtual": false, "openHour": "5 gi\u1edd 30 ph\u00fat - 21 gi\u1edd (k\u1ec3 c\u1ea3 CN v\u00e0 ng\u00e0y l\u1ec5)"}, {"storeId": 7317, "lat": 11.475653, "lng": 107.90294, "storeLocation": "BHX H\u00f2a Nam (S\u1ed1 01-02 Th\u00f4n 02, X\u00e3 H\u00f2a Nam, Huy\u1ec7n Di Linh, T\u1ec9nh L\u00e2m \u0110\u1ed3ng (\u0111\u1ed1i di\u1ec7n ch\u1ee3 Ho\u00e0 Nam))", "provinceId": 129, "districtId": 1114, "wardId": 5391, "isStoreVirtual": false, "openHour": "5 gi\u1edd 30 ph\u00fat - 20 gi\u1edd 30 ph\u00fat (k\u1ec3 c\u1ea3 CN v\u00e0 ng\u00e0y l\u1ec5)"}, {"storeId": 6969, "lat": 11.546589, "lng": 107.90057, "storeLocation": "BHX Qu\u1ed1c L\u1ed9 20 L\u1ed9c An (Th\u00f4n 7, X\u00e3 L\u1ed9c An, Huy\u1ec7n B\u1ea3o L\u00e2m, T\u1ec9nh L\u00e2m \u0110\u1ed3ng (c\u00e1ch ch\u1ee3 c\u0169 L\u1ed9c An 200m))", "provinceId": 129, "districtId": 1107, "wardId": 11172, "isStoreVirtual": false, "openHour": "5 gi\u1edd 30 ph\u00fat - 21 gi\u1edd (k\u1ec3 c\u1ea3 CN v\u00e0 ng\u00e0y l\u1ec5)"}, {"storeId": 7333, "lat": 11.730736, "lng": 108.37255, "storeLocation": "BHX 245 Li\u00ean Ngh\u0129a (Khu ph\u1ed1 2, TT. Li\u00ean Ngh\u0129a, Huy\u1ec7n \u0110\u1ee9c Tr\u1ecdng, T\u1ec9nh L\u00e2m \u0110\u1ed3ng (k\u1ebf b\u00ean \u0110i\u1ec7n M\u00e1y XANH))", "provinceId": 129, "districtId": 1116, "wardId": 5411, "isStoreVirtual": false, "openHour": "5 gi\u1edd 30 ph\u00fat - 21 gi\u1edd 30 ph\u00fat (k\u1ec3 c\u1ea3 CN v\u00e0 ng\u00e0y l\u1ec5)"}, {"storeId": 7040, "lat": 11.942775, "lng": 108.42799, "storeLocation": "BHX 40 Ph\u01b0\u1eddng 5 (S\u1ed1 45 Ho\u00e0ng Di\u1ec7u, Ph\u01b0\u1eddng 5, TP. \u0110\u00e0 L\u1ea1t, T\u1ec9nh L\u00e2m \u0110\u1ed3ng (b\u00ean c\u1ea1nh ch\u1ee3 M\u1ef9 Th\u00e0nh))", "provinceId": 129, "districtId": 1111, "wardId": 5455, "isStoreVirtual": false, "openHour": "5 gi\u1edd 30 ph\u00fat - 21 gi\u1edd 30 ph\u00fat (k\u1ec3 c\u1ea3 CN v\u00e0 ng\u00e0y l\u1ec5)"}, {"storeId": 6890, "lat": 11.757213, "lng": 108.529274, "storeLocation": "BHX Nam Hi\u1ec7p 1 (Ka \u0110\u00f4) (373 X\u00f3m 7, Th\u00f4n Nam Hi\u1ec7p 1, X\u00e3 Ka \u0110\u00f4, Huy\u1ec7n \u0110\u01a1n D\u01b0\u01a1ng, T\u1ec9nh L\u00e2m \u0110\u1ed3ng (ngay ng\u00e3 ba T\u00ecnh Ka \u0110\u00f4))", "provinceId": 129, "districtId": 1115, "wardId": 5404, "isStoreVirtual": false, "openHour": "5 gi\u1edd 30 ph\u00fat - 21 gi\u1edd 30 ph\u00fat (k\u1ec3 c\u1ea3 CN v\u00e0 ng\u00e0y l\u1ec5)"}, {"storeId": 7157, "lat": 11.582652, "lng": 107.36315, "storeLocation": "BHX 208 Ph\u1ea1m V\u0103n \u0110\u1ed3ng (S\u1ed1 208 - 210 Ph\u1ea1m V\u0103n \u0110\u1ed3ng, TT. C\u00e1t Ti\u00ean, Huy\u1ec7n C\u00e1t Ti\u00ean, T\u1ec9nh L\u00e2m \u0110\u1ed3ng (c\u00e1ch ch\u1ee3 C\u00e1t Ti\u00ean 50m))", "provinceId": 129, "districtId": 1109, "wardId": 5341, "isStoreVirtual": false, "openHour": "5 gi\u1edd 30 ph\u00fat - 21 gi\u1edd (k\u1ec3 c\u1ea3 CN v\u00e0 ng\u00e0y l\u1ec5)"}, {"storeId": 7109, "lat": 11.539253, "lng": 107.94341, "storeLocation": "BHX Qu\u1ed1c L\u1ed9 20 (H\u00f2a Ninh) (QL20, Th\u00f4n 2, X\u00e3 H\u00f2a Ninh, Huy\u1ec7n Di Linh, T\u1ec9nh L\u00e2m \u0110\u1ed3ng (ngay ng\u00e3 ba Ho\u00e0 Ninh))", "provinceId": 129, "districtId": 1114, "wardId": 5392, "isStoreVirtual": false, "openHour": "5 gi\u1edd 30 ph\u00fat - 21 gi\u1edd (k\u1ec3 c\u1ea3 CN v\u00e0 ng\u00e0y l\u1ec5)"}, {"storeId": 7166, "lat": 11.776009, "lng": 108.28883, "storeLocation": "BHX Qu\u1ed1c L\u1ed9 27 B\u00ecnh Th\u1ea1nh (S\u1ed1 67 \u0110\u01b0\u1eddng QL27, Th\u00f4n Thanh B\u00ecnh 2, X\u00e3 B\u00ecnh Th\u1ea1nh, Huy\u1ec7n \u0110\u1ee9c Tr\u1ecdng, T\u1ec9nh L\u00e2m \u0110\u1ed3ng (ngay ch\u1ee3 B\u00ecnh Th\u1ea1nh))", "provinceId": 129, "districtId": 1116, "wardId": 5412, "isStoreVirtual": false, "openHour": "5 gi\u1edd 30 ph\u00fat - 20 gi\u1edd 30 ph\u00fat (k\u1ec3 c\u1ea3 CN v\u00e0 ng\u00e0y l\u1ec5)"}, {"storeId": 7006, "lat": 11.512351, "lng": 107.75, "storeLocation": "BHX 1134 QL20 \u0110\u1ea1i L\u00e0o (S\u1ed1 1134 - 1134a QL20, X\u00e3 \u0110\u1ea1i L\u00e0o, TP. B\u1ea3o L\u1ed9c, T\u1ec9nh L\u00e2m \u0110\u1ed3ng (ngay ch\u1ee3 \u0110\u1ea1i L\u00e0o))", "provinceId": 129, "districtId": 1108, "wardId": 5470, "isStoreVirtual": false, "openHour": "5 gi\u1edd 30 ph\u00fat - 21 gi\u1edd (k\u1ec3 c\u1ea3 CN v\u00e0 ng\u00e0y l\u1ec5)"}, {"storeId": 7716, "lat": 11.946113, "lng": 108.49952, "storeLocation": "BHX 416 Ph\u01b0\u1eddng 11 (S\u1ed1 107 - 109/5 T\u1ef1 Ph\u01b0\u1edbc, Ph\u01b0\u1eddng 11, TP. \u0110\u00e0 L\u1ea1t, T\u1ec9nh L\u00e2m \u0110\u1ed3ng (B\u00ean c\u1ea1nh ch\u1ee3 Tr\u1ea1i M\u00e1t))", "provinceId": 129, "districtId": 1111, "wardId": 5450, "isStoreVirtual": false, "openHour": "5 gi\u1edd 30 ph\u00fat - 21 gi\u1edd 30 ph\u00fat (k\u1ec3 c\u1ea3 CN v\u00e0 ng\u00e0y l\u1ec5)"}, {"storeId": 7237, "lat": 11.627823, "lng": 108.18184, "storeLocation": "BHX Ph\u00fa Hi\u1ec7p 3 (Gia Hi\u1ec7p) (S\u1ed1 2 Th\u00f4n Ph\u00fa Hi\u1ec7p 3, X\u00e3 Gia Hi\u1ec7p, Huy\u1ec7n Di Linh, T\u1ec9nh L\u00e2m \u0110\u1ed3ng (ngay ch\u1ee3 Gia Hi\u1ec7p))", "provinceId": 129, "districtId": 1114, "wardId": 5388, "isStoreVirtual": false, "openHour": "5 gi\u1edd 30 ph\u00fat - 20 gi\u1edd 30 ph\u00fat (k\u1ec3 c\u1ea3 CN v\u00e0 ng\u00e0y l\u1ec5)"}, {"storeId": 7817, "lat": 11.410855, "lng": 107.6596, "storeLocation": "BHX 276 L\u00ea L\u1ee3i (S\u1ed1 276 L\u00ea L\u1ee3i, TT. \u0110\u1ea1 M'Ri, Huy\u1ec7n \u0110\u1ea1 Huoai, T\u1ec9nh L\u00e2m \u0110\u1ed3ng (c\u00e1ch ch\u1ee3 TT \u0110\u1ea1 M'Ri 100m))", "provinceId": 129, "districtId": 1110, "wardId": 5353, "isStoreVirtual": false, "openHour": "5 gi\u1edd 30 ph\u00fat - 20 gi\u1edd 30 ph\u00fat (k\u1ec3 c\u1ea3 CN v\u00e0 ng\u00e0y l\u1ec5)"}, {"storeId": 7844, "lat": 11.531196, "lng": 107.86468, "storeLocation": "BHX \u0110\u1ea1i Nga (Ch\u1ee3 L\u1ed9c Nga) (X\u00e3 L\u1ed9c Nga, TP. B\u1ea3o L\u1ed9c, T\u1ec9nh L\u00e2m \u0110\u1ed3ng (ngay ch\u1ee3 L\u1ed9c Nga))", "provinceId": 129, "districtId": 1108, "wardId": 5473, "isStoreVirtual": false, "openHour": "5 gi\u1edd 30 ph\u00fat - 21 gi\u1edd (k\u1ec3 c\u1ea3 CN v\u00e0 ng\u00e0y l\u1ec5)"}, {"storeId": 7863, "lat": 11.747347, "lng": 108.19697, "storeLocation": "BHX Li\u00ean Trung (T\u00e2n H\u00e0) (Th\u00f4n Li\u00ean Trung, X\u00e3 T\u00e2n H\u00e0, Huy\u1ec7n L\u00e2m H\u00e0, T\u1ec9nh L\u00e2m \u0110\u1ed3ng (c\u00e1ch ch\u1ee3 T\u00e2n H\u00e0 150m))", "provinceId": 129, "districtId": 1118, "wardId": 5445, "isStoreVirtual": false, "openHour": "5 gi\u1edd 30 ph\u00fat - 21 gi\u1edd 30 ph\u00fat (k\u1ec3 c\u1ea3 CN v\u00e0 ng\u00e0y l\u1ec5)"}, {"storeId": 7254, "lat": 12.007639, "lng": 108.41925, "storeLocation": "BHX 76 Langbiang (S\u1ed1 76 Langbiang, TT. L\u1ea1c D\u01b0\u01a1ng, Huy\u1ec7n L\u1ea1c D\u01b0\u01a1ng, T\u1ec9nh L\u00e2m \u0110\u1ed3ng (b\u00ean c\u1ea1nh \u0110i\u1ec7n M\u00e1y XANH))", "provinceId": 129, "districtId": 1117, "wardId": 5426, "isStoreVirtual": false, "openHour": "5 gi\u1edd 30 ph\u00fat - 21 gi\u1edd 30 ph\u00fat (k\u1ec3 c\u1ea3 CN v\u00e0 ng\u00e0y l\u1ec5)"}, {"storeId": 7669, "lat": 11.711755, "lng": 108.29191, "storeLocation": "BHX T\u00e2n H\u1ed9i (Khu trung t\u00e2m th\u01b0\u01a1ng m\u1ea1i x\u00e3 T\u00e2n H\u1ed9i, X\u00e3 T\u00e2n H\u1ed9i, Huy\u1ec7n \u0110\u1ee9c Tr\u1ecdng, T\u1ec9nh L\u00e2m \u0110\u1ed3ng (c\u00e1ch ch\u1ee3 T\u00e2n H\u1ed9i 100m))", "provinceId": 129, "districtId": 1116, "wardId": 5424, "isStoreVirtual": false, "openHour": "5 gi\u1edd 30 ph\u00fat - 20 gi\u1edd 30 ph\u00fat (k\u1ec3 c\u1ea3 CN v\u00e0 ng\u00e0y l\u1ec5)"}, {"storeId": 7862, "lat": 11.764357, "lng": 108.37071, "storeLocation": "BHX 35/6 Li\u00ean Hi\u1ec7p (S\u1ed1 35/6 Th\u00f4n An Hi\u1ec7p, X\u00e3 Li\u00ean Hi\u1ec7p, Huy\u1ec7n \u0110\u1ee9c Tr\u1ecdng, T\u1ec9nh L\u00e2m \u0110\u1ed3ng (ngay ng\u00e3 ba C\u1ed5ng V\u00e0ng))", "provinceId": 129, "districtId": 1116, "wardId": 5417, "isStoreVirtual": false, "openHour": "5 gi\u1edd 30 ph\u00fat - 21 gi\u1edd (k\u1ec3 c\u1ea3 CN v\u00e0 ng\u00e0y l\u1ec5)"}, {"storeId": 7667, "lat": 11.42178, "lng": 107.86019, "storeLocation": "BHX 336 L\u1ed9c Nam (X\u00e3 L\u1ed9c Nam, Huy\u1ec7n B\u1ea3o L\u00e2m, T\u1ec9nh L\u00e2m \u0110\u1ed3ng (c\u00e1ch nh\u00e0 h\u00e0ng ti\u1ec7c c\u01b0\u1edbi Thanh Nguy\u00ean 150m))", "provinceId": 129, "districtId": 1107, "wardId": 11169, "isStoreVirtual": false, "openHour": "5 gi\u1edd 30 ph\u00fat - 21 gi\u1edd 30 ph\u00fat (k\u1ec3 c\u1ea3 CN v\u00e0 ng\u00e0y l\u1ec5)"}, {"storeId": 7994, "lat": 11.505, "lng": 107.48756, "storeLocation": "BHX Khu Ph\u1ed1 5C (\u0110\u1ea1 T\u1ebbh) (Khu ph\u1ed1 5C, TT. \u0110\u1ea1 T\u1ebbh, Huy\u1ec7n \u0110\u1ea1 T\u1ebbh, T\u1ec9nh L\u00e2m \u0110\u1ed3ng (ngay v\u00f2ng xoay ch\u1ee3 \u0110\u1ea1 T\u1ebbh))", "provinceId": 129, "districtId": 1112, "wardId": 5363, "isStoreVirtual": false, "openHour": "5 gi\u1edd 30 ph\u00fat - 21 gi\u1edd 30 ph\u00fat (k\u1ec3 c\u1ea3 CN v\u00e0 ng\u00e0y l\u1ec5)"}, {"storeId": 7668, "lat": 11.565418, "lng": 107.31232, "storeLocation": "BHX 90 Ph\u01b0\u1edbc C\u00e1t (S\u1ed1 90 T\u1ed5 d\u00e2n ph\u1ed1 5, TT. Ph\u01b0\u1edbc C\u00e1t, Huy\u1ec7n C\u00e1t Ti\u00ean, T\u1ec9nh L\u00e2m \u0110\u1ed3ng (ngay ng\u00e3 t\u01b0 C\u00e2y G\u00f2n))", "provinceId": 129, "districtId": 1109, "wardId": 5348, "isStoreVirtual": false, "openHour": "5 gi\u1edd 30 ph\u00fat - 21 gi\u1edd (k\u1ec3 c\u1ea3 CN v\u00e0 ng\u00e0y l\u1ec5)"}, {"storeId": 7819, "lat": 11.592117, "lng": 108.07837, "storeLocation": "BHX 775 H\u00f9ng V\u01b0\u01a1ng (S\u1ed1 777 H\u00f9ng V\u01b0\u01a1ng, T\u1ed5 d\u00e2n ph\u1ed1 14, TT. Di Linh, Huy\u1ec7n Di Linh, T\u1ec9nh L\u00e2m \u0110\u1ed3ng (c\u00e1ch ch\u1ee3 Di Linh 150m))", "provinceId": 129, "districtId": 1114, "wardId": 5382, "isStoreVirtual": false, "openHour": "5 gi\u1edd 30 ph\u00fat - 21 gi\u1edd 30 ph\u00fat (k\u1ec3 c\u1ea3 CN v\u00e0 ng\u00e0y l\u1ec5)"}, {"storeId": 8039, "lat": 11.58164, "lng": 108.07545, "storeLocation": "BHX 23 L\u00fd Th\u01b0\u1eddng Ki\u1ec7t (S\u1ed1 23 L\u00fd Th\u01b0\u1eddng Ki\u1ec7t, TT. Di Linh, Huy\u1ec7n Di Linh, T\u1ec9nh L\u00e2m \u0110\u1ed3ng (c\u00e1ch ng\u00e3 3 ch\u1ee3 c\u0169 Di Linh 100m))", "provinceId": 129, "districtId": 1114, "wardId": 5382, "isStoreVirtual": false, "openHour": "5 gi\u1edd 30 ph\u00fat - 21 gi\u1edd 30 ph\u00fat (k\u1ec3 c\u1ea3 CN v\u00e0 ng\u00e0y l\u1ec5)"}, {"storeId": 8210, "lat": 11.788793, "lng": 108.24297, "storeLocation": "BHX 368 \u0110inh V\u0103n (Th\u1ecb Tr\u1ea5n \u0110inh V\u0103n, Huy\u1ec7n L\u00e2m H\u00e0, T\u1ec9nh L\u00e2m \u0110\u1ed3ng (\u0111\u1ed1i di\u1ec7n ch\u1ee3 L\u00e2m H\u00e0))", "provinceId": 129, "districtId": 1118, "wardId": 5432, "isStoreVirtual": false, "openHour": "5 gi\u1edd 30 ph\u00fat - 21 gi\u1edd 30 ph\u00fat (k\u1ec3 c\u1ea3 CN v\u00e0 ng\u00e0y l\u1ec5)"}, {"storeId": 8154, "lat": 11.845664, "lng": 108.60365, "storeLocation": "BHX 317 Dran (S\u1ed1 45 Tr\u1ea7n H\u01b0ng \u0110\u1ea1o, TT. D'Ran, Huy\u1ec7n \u0110\u01a1n D\u01b0\u01a1ng, T\u1ec9nh L\u00e2m \u0110\u1ed3ng (\u0111\u1ed1i di\u1ec7n tr\u01b0\u1eddng THPT L\u1ea1c Nghi\u1ec7p))", "provinceId": 129, "districtId": 1115, "wardId": 5401, "isStoreVirtual": false, "openHour": "5 gi\u1edd 30 ph\u00fat - 20 gi\u1edd 30 ph\u00fat (k\u1ec3 c\u1ea3 CN v\u00e0 ng\u00e0y l\u1ec5)"}, {"storeId": 9103, "lat": 12.180729, "lng": 108.13762, "storeLocation": "BHX \u0110\u1ea1 RSal (Th\u00f4n Phi C\u00f3, X\u00e3 \u0110\u1ea1 RSal, Huy\u1ec7n \u0110am R\u00f4ng, T\u1ec9nh L\u00e2m \u0110\u1ed3ng (\u0110\u1ed1i di\u1ec7n ch\u1ee3 \u0110\u1ea1 RSal))", "provinceId": 129, "districtId": 1113, "wardId": 5377, "isStoreVirtual": false, "openHour": "5 gi\u1edd 30 ph\u00fat - 21 gi\u1edd 30 ph\u00fat (k\u1ec3 c\u1ea3 CN v\u00e0 ng\u00e0y l\u1ec5)"}, {"storeId": 9254, "lat": 11.383511, "lng": 107.532486, "storeLocation": "BHX Ma \u0110a Gu\u00f4i (Th\u1ecb Tr\u1ea5n Ma \u0110a Gu\u00f4i, Huy\u1ec7n \u0110\u1ea1 Huoai, t\u1ec9nh L\u00e2m \u0110\u1ed3ng (\u0110\u1ed1i di\u1ec7n ng\u00e2n h\u00e0ng Agribank))", "provinceId": 129, "districtId": 1110, "wardId": 5354, "isStoreVirtual": false, "openHour": "5 gi\u1edd 30 ph\u00fat - 21 gi\u1edd 30 ph\u00fat (k\u1ec3 c\u1ea3 CN v\u00e0 ng\u00e0y l\u1ec5)"}, {"storeId": 9576, "lat": 11.88568, "lng": 108.550224, "storeLocation": "BHX Xu\u00e2n Tr\u01b0\u1eddng (123/3 th\u00f4n Tr\u01b0\u1eddng Xu\u00e2n 1, X\u00e3 Xu\u00e2n Tr\u01b0\u1eddng, Th\u00e0nh ph\u1ed1 \u0110\u00e0 L\u1ea1t, T\u1ec9nh L\u00e2m \u0110\u1ed3ng, Vi\u1ec7t Nam)", "provinceId": 129, "districtId": 1111, "wardId": 5463, "isStoreVirtual": false, "openHour": "5 gi\u1edd 30 ph\u00fat - 20 gi\u1edd 30 ph\u00fat (k\u1ec3 c\u1ea3 CN v\u00e0 ng\u00e0y l\u1ec5)"}, {"storeId": 9625, "lat": 11.821783, "lng": 108.336205, "storeLocation": "BHX Gia L\u00e2m (\u0110\u01b0\u1eddng t\u1ec9nh 725, Th\u00f4n Quang Trung 1, x\u00e3 Gia L\u00e2m, huy\u1ec7n L\u00e2m H\u00e0, L\u00e2m \u0110\u1ed3ng)", "provinceId": 129, "districtId": 1118, "wardId": 5437, "isStoreVirtual": false, "openHour": "5 gi\u1edd 30 ph\u00fat - 20 gi\u1edd 30 ph\u00fat (k\u1ec3 c\u1ea3 CN v\u00e0 ng\u00e0y l\u1ec5)"}, {"storeId": 9149, "lat": 12.059409, "lng": 108.1472, "storeLocation": "BHX R\u00f4men (Th\u1eeda s\u1ed1 111, t\u1edd b\u1ea3n \u0111\u1ed3 20, Th\u00f4n 1, X\u00e3 R\u00f4men, Huy\u1ec7n \u0110am R\u00f4ng, T\u1ec9nh L\u00e2m \u0110\u1ed3ng (\u0110\u1ed1i di\u1ec7n ch\u1ee3 R\u00f4men))", "provinceId": 129, "districtId": 1113, "wardId": 5381, "isStoreVirtual": false, "openHour": "5 gi\u1edd 30 ph\u00fat - 20 gi\u1edd 30 ph\u00fat (k\u1ec3 c\u1ea3 CN v\u00e0 ng\u00e0y l\u1ec5)"}, {"storeId": 8711, "lat": 11.96252, "lng": 108.44363, "storeLocation": "BHX Ph\u00f9 \u0110\u1ed5ng Thi\u00ean V\u01b0\u01a1ng (Khu quy ho\u1ea1ch 26, Ph\u00f9 \u0110\u1ed5ng Thi\u00ean V\u01b0\u01a1ng, Ph\u01b0\u1eddng 8, Th\u00e0nh ph\u1ed1 \u0110\u00e0 L\u1ea1t, T\u1ec9nh L\u00e2m \u0110\u1ed3ng (C\u00e1ch UBND Ph\u01b0\u1eddng 8 50m))", "provinceId": 129, "districtId": 1111, "wardId": 5458, "isStoreVirtual": false, "openHour": "5 gi\u1edd 30 ph\u00fat - 21 gi\u1edd 30 ph\u00fat (k\u1ec3 c\u1ea3 CN v\u00e0 ng\u00e0y l\u1ec5)"}, {"storeId": 9371, "lat": 11.939444, "lng": 108.136475, "storeLocation": "BHX Phi Li\u00eang (x\u00e3 Phi Li\u00eang, Huy\u1ec7n \u0110am R\u00f4ng, t\u1ec9nh L\u00e2m \u0110\u1ed3ng (Ngay ch\u1ee3 Phi Li\u00eang))", "provinceId": 129, "districtId": 1113, "wardId": 5380, "isStoreVirtual": false, "openHour": "5 gi\u1edd 30 ph\u00fat - 20 gi\u1edd 30 ph\u00fat (k\u1ec3 c\u1ea3 CN v\u00e0 ng\u00e0y l\u1ec5)"}, {"storeId": 8746, "lat": 11.961364, "lng": 108.471306, "storeLocation": "BHX 67 M\u00ea Linh (S\u1ed1 67 M\u00ea Linh, Ph\u01b0\u1eddng 9, TP. \u0110\u00e0 L\u1ea1t, T\u1ec9nh L\u00e2m \u0110\u1ed3ng (c\u00e1ch c\u1ed5ng ch\u00e0o TDP 2 - 50m))", "provinceId": 129, "districtId": 1111, "wardId": 5459, "isStoreVirtual": false, "openHour": "5 gi\u1edd 30 ph\u00fat - 21 gi\u1edd 30 ph\u00fat (k\u1ec3 c\u1ea3 CN v\u00e0 ng\u00e0y l\u1ec5)"}, {"storeId": 9734, "lat": 11.783194, "lng": 108.41094, "storeLocation": "BHX Hi\u1ec7p Th\u1ea1nh (Th\u1eeda \u0111\u1ea5t s\u1ed1 1877, T\u1edd b\u1ea3n \u0111\u1ed3 s\u1ed1 01, Th\u00f4n Phi N\u00f4m, X\u00e3 Hi\u1ec7p Th\u1ea1nh , Huy\u1ec7n \u0110\u1ee9c Tr\u1ecdng , L\u00e2m \u0110\u1ed3ng)", "provinceId": 129, "districtId": 1116, "wardId": 5416, "isStoreVirtual": false, "openHour": "5 gi\u1edd 30 ph\u00fat - 21 gi\u1edd 30 ph\u00fat (k\u1ec3 c\u1ea3 CN v\u00e0 ng\u00e0y l\u1ec5)"}, {"storeId": 9731, "lat": 11.727278, "lng": 108.3765, "storeLocation": "BHX Li\u00ean Ngh\u0129a ( \u0111\u1ea5t s\u1ed1 1643) (Th\u1eeda \u0111\u1ea5t s\u1ed1 1643, t\u1edd b\u1ea3n \u0111\u1ed3 s\u1ed1 15, th\u1ecb Tr\u1ea5n Li\u00ean Ngh\u0129a, huy\u1ec7n \u0110\u1ee9c Tr\u1ecdng, t\u1ec9nh L\u00e2m \u0110\u1ed3ng)", "provinceId": 129, "districtId": 1116, "wardId": 5411, "isStoreVirtual": false, "openHour": "5 gi\u1edd 30 ph\u00fat - 21 gi\u1edd 30 ph\u00fat (k\u1ec3 c\u1ea3 CN v\u00e0 ng\u00e0y l\u1ec5)"}, {"storeId": 7238, "lat": 11.628648, "lng": 107.83833, "storeLocation": "BHX L\u1ed9c Th\u1eafng (Khu 02, Th\u1ecb Tr\u1ea5n L\u1ed9c Th\u1eafng, Huy\u1ec7n B\u1ea3o L\u00e2m, T\u1ec9nh L\u00e2m \u0110\u1ed3ng (\u0110\u1ed1i di\u1ec7n c\u1ed5ng ch\u00e0o Huy\u1ec7n B\u1ea3o L\u00e2m ( C\u00e1ch ch\u1ee3 B\u1ea3o L\u00e2m 150m)))", "provinceId": 129, "districtId": 1107, "wardId": 11177, "isStoreVirtual": false, "openHour": "5 gi\u1edd 30 ph\u00fat - 21 gi\u1edd 30 ph\u00fat (k\u1ec3 c\u1ea3 CN v\u00e0 ng\u00e0y l\u1ec5)"}, {"storeId": 9202, "lat": 11.954271, "lng": 108.44131, "storeLocation": "BHX 63 B\u00f9i Th\u1ecb Xu\u00e2n (S\u1ed1 63 B\u00f9i Th\u1ecb Xu\u00e2n, ph\u01b0\u1eddng 2, th\u00e0nh ph\u1ed1 \u0110\u00e0 L\u1ea1t, t\u1ec9nh L\u00e2m \u0110\u1ed3ng (B\u00ean c\u1ea1nh Tr\u01b0\u1eddng Ti\u1ec3u h\u1ecdc Nguy\u1ec5n Tr\u00e3i))", "provinceId": 129, "districtId": 1111, "wardId": 5452, "isStoreVirtual": false, "openHour": "5 gi\u1edd 30 ph\u00fat - 21 gi\u1edd 30 ph\u00fat (k\u1ec3 c\u1ea3 CN v\u00e0 ng\u00e0y l\u1ec5)"}, {"storeId": 8901, "lat": 11.786509, "lng": 108.2503, "storeLocation": "BHX Qu\u1ea3ng \u0110\u1ee9c (Th\u1eeda \u0111\u1ea5t s\u1ed1 554 v\u00e0 555, t\u1edd b\u1ea3n \u0111\u1ed3 s\u1ed1 63, TDP Qu\u1ea3ng \u0110\u1ee9c, Th\u1ecb tr\u1ea5n \u0110inh V\u0103n, Huy\u1ec7n L\u00e2m H\u00e0, T\u1ec9nh L\u1ea7m \u0110\u1ed3ng)", "provinceId": 129, "districtId": 1118, "wardId": 5432, "isStoreVirtual": false, "openHour": "5 gi\u1edd 30 ph\u00fat - 21 gi\u1edd 30 ph\u00fat (k\u1ec3 c\u1ea3 CN v\u00e0 ng\u00e0y l\u1ec5)"}, {"storeId": 6224, "lat": 11.632274, "lng": 108.304726, "storeLocation": "BHX 38 Ninh Gia (QL20, X\u00e3 Ninh Gia, Huy\u1ec7n \u0110\u1ee9c Tr\u1ecdng, T\u1ec9nh L\u00e2m \u0110\u1ed3ng (ngay ch\u1ee3 Ninh Gia))", "provinceId": 129, "districtId": 1116, "wardId": 5418, "isStoreVirtual": false, "openHour": "5 gi\u1edd 30 ph\u00fat - 20 gi\u1edd 30 ph\u00fat (k\u1ec3 c\u1ea3 CN v\u00e0 ng\u00e0y l\u1ec5)"}, {"storeId": 8040, "lat": 11.676059, "lng": 107.98588, "storeLocation": "BHX 84 Th\u00f4n 3 (T\u00e2n L\u00e2m) (84 Th\u00f4n 3, X\u00e3 T\u00e2n L\u00e2m, Huy\u1ec7n Di Linh, T\u1ec9nh L\u00e2m \u0110\u1ed3ng (c\u00e1ch tr\u01b0\u1eddng ti\u1ec3u h\u1ecdc T\u00e2n L\u00e2m 100m))", "provinceId": 129, "districtId": 1114, "wardId": 5398, "isStoreVirtual": false, "openHour": "5 gi\u1edd 30 ph\u00fat - 20 gi\u1edd 30 ph\u00fat (k\u1ec3 c\u1ea3 CN v\u00e0 ng\u00e0y l\u1ec5)"}]